feaASTools/__init__.py
feaASTools/inspect.py
feaASTools/renameGlyph.py
feaASTools-0.2.7.dist-info/LICENSE
feaASTools-0.2.7.dist-info/METADATA
feaASTools-0.2.7.dist-info/WHEEL
feaASTools-0.2.7.dist-info/top_level.txt
feaASTools-0.2.7.dist-info/RECORD
